scrum_o_tron-0.0.2.dist-info/DESCRIPTION.rst
scrum_o_tron-0.0.2.dist-info/METADATA
scrum_o_tron-0.0.2.dist-info/RECORD
scrum_o_tron-0.0.2.dist-info/WHEEL
scrum_o_tron-0.0.2.dist-info/entry_points.txt
scrum_o_tron-0.0.2.dist-info/metadata.json
scrum_o_tron-0.0.2.dist-info/top_level.txt
scrumotron/__init__.py
scrumotron/cli.py
scrumotron/version.txt
